{
    "Name": "Virtual Machine Operator",
    "IsCustom": true,
    "Description": "Can start, stop virtual machines and create support request.",
    "Actions": [
        "Microsoft.Compute/virtualMachines/read",
        "Microsoft.Compute/virtualMachines/start/action",
        "Microsoft.Compute/virtualMachines/powerOff/action",
        "Microsoft.Support/write"
    ],
    "NotActions": [],
    "DataActions": [],
    "NotDataActions": [],
    "AssignableScopes": [
      "/subscriptions/{60dd9fa3-8b3f-46cc-bcdb-438efcbf1939}"
    ]
  }
